smartleia/__init__.py
smartleia/__main__.py
smartleia/test_applet.py
smartleia-1.0.2.dist-info/AUTHORS
smartleia-1.0.2.dist-info/LICENSE.bsd3
smartleia-1.0.2.dist-info/LICENSE.lgpl-2.1+
smartleia-1.0.2.dist-info/METADATA
smartleia-1.0.2.dist-info/WHEEL
smartleia-1.0.2.dist-info/top_level.txt
smartleia-1.0.2.dist-info/RECORD
