Metadata-Version: 2.1
Name: smartleia
Version: 1.0.2
Summary: Python toolkit for LEIA smartcard reader
Author: LEIA Team
Author-email: leia@h2lab.org
License: LGPL-2.1+
Project-URL: homepage, https://h2lab.org/devices/leia/quickstart/
Project-URL: repository, https://github.com/h2lab/smartleia
Requires-Python: ==3.*,>=3.6.0
License-File: LICENSE.bsd3
License-File: LICENSE.lgpl-2.1+
License-File: AUTHORS
Requires-Dist: pyserial ==3.*,>=3.4.0
Provides-Extra: dev
Requires-Dist: dephell ==0.*,>=0.8.3 ; extra == 'dev'
Requires-Dist: black ==19.*,>=19.10.0.b0 ; extra == 'dev'
Requires-Dist: bump2version ==1.*,>=1.0.0 ; extra == 'dev'
Requires-Dist: coverage ==5.*,>=5.1.0 ; extra == 'dev'
Requires-Dist: flake8 ==3.*,>=3.7.9 ; extra == 'dev'
Requires-Dist: ipython ==7.*,>=7.14.0 ; extra == 'dev'
Requires-Dist: mypy ==0.*,>=0.770.0 ; extra == 'dev'
Requires-Dist: nbsphinx ==0.*,>=0.7.0 ; extra == 'dev'
Requires-Dist: pandoc ==1.*,>=1.0.2 ; extra == 'dev'
Requires-Dist: pre-commit ==2.*,>=2.3.0 ; extra == 'dev'
Requires-Dist: pylint ==2.*,>=2.5.2 ; extra == 'dev'
Requires-Dist: pytest-runner ==5.*,>=5.2.0 ; extra == 'dev'
Requires-Dist: recommonmark ==0.*,>=0.6.0 ; extra == 'dev'
Requires-Dist: sphinx ==3.*,>=3.0.0 ; extra == 'dev'
Requires-Dist: sphinx-autodoc-typehints ==1.*,>=1.10.3 ; extra == 'dev'
Requires-Dist: sphinx-rtd-theme ==0.*,>=0.5.0 ; extra == 'dev'
Requires-Dist: sphinxcontrib.spelling ==5.*,>=5.0.0 ; extra == 'dev'
Requires-Dist: sphinxcontrib.wavedrom ==2.*,>=2.1.0 ; extra == 'dev'
Provides-Extra: test
Requires-Dist: pytest ==5.*,>=5.2.0 ; extra == 'test'
Requires-Dist: pytest-csv ==2.*,>=2.0.2 ; extra == 'test'
